taskjuggler_python/__init__.py
taskjuggler_python/__main__.py
taskjuggler_python/jirajuggler.py
taskjuggler_python/jsonjuggler.py
taskjuggler_python/juggler.py
taskjuggler_python/tjpy_client.py
taskjuggler_python/tests/__init__.py
taskjuggler_python/tests/conftest.py
taskjuggler_python/tests/test_jsonjuggler.py
taskjuggler_python/tests/test_juggler.py
taskjuggler_python-0.0.2.dist-info/DESCRIPTION.rst
taskjuggler_python-0.0.2.dist-info/METADATA
taskjuggler_python-0.0.2.dist-info/RECORD
taskjuggler_python-0.0.2.dist-info/WHEEL
taskjuggler_python-0.0.2.dist-info/entry_points.txt
taskjuggler_python-0.0.2.dist-info/metadata.json
taskjuggler_python-0.0.2.dist-info/top_level.txt
tests/__init__.py
tests/conftest.py
tests/test_cli.py
