Metadata-Version: 2.0
Name: taskjuggler-python
Version: 0.0.2
Summary: Python interfaces to TaskJuggler 3 planner
Home-page: https://github.com/grandrew/taskjuggler-python
Author: Andrew Gryaznov
Author-email: realgrandrew@gmail.com
License: MIT
Platform: UNKNOWN
Classifier: Development Status :: 1 - Planning
Classifier: Natural Language :: English
Classifier: Operating System :: OS Independent
Classifier: Programming Language :: Python
Classifier: Programming Language :: Python :: 2
Classifier: Programming Language :: Python :: 2.7
Requires-Dist: icalendar (>=3.11)
Requires-Dist: airtable-python-wrapper (>=0.8)
Requires-Dist: python-dateutil (>=2.6)
